MapleStoryPython/IOTool.py
MapleStoryPython/__init__.py
MapleStoryPython/toolRoot.py
MapleStoryPython-2.0.1.dist-info/LICENSE
MapleStoryPython-2.0.1.dist-info/METADATA
MapleStoryPython-2.0.1.dist-info/WHEEL
MapleStoryPython-2.0.1.dist-info/top_level.txt
MapleStoryPython-2.0.1.dist-info/RECORD
