Metadata-Version: 2.1
Name: MapleStoryPython
Version: 2.0.1
Summary: No description.
Home-page: https://github.com/a405457747/MapleStoryPython
Author: skyAllen
Author-email: 894982165@qq.com
Classifier: Programming Language :: Python :: 3
Classifier: License :: OSI Approved :: MIT License
Classifier: Operating System :: OS Independent
Requires-Python: >=3.7
License-File: LICENSE
